cataloguer/__init__.py
cataloguer/__main__.py
cataloguer/cli.py
cataloguer/api/__init__.py
cataloguer/api/app.py
cataloguer/api/deps.py
cataloguer/api/routes/__init__.py
cataloguer/api/routes/images.py
cataloguer/api/routes/items.py
cataloguer/api/routes/locations.py
cataloguer/api/routes/search.py
cataloguer/api/static/index.html
cataloguer/database/__init__.py
cataloguer/database/models.py
cataloguer/processor/__init__.py
cataloguer/processor/classifier.py
cataloguer/processor/identifier.py
cataloguer/processor/pipeline.py
visual_cataloguer-0.8.0.dist-info/METADATA
visual_cataloguer-0.8.0.dist-info/WHEEL
visual_cataloguer-0.8.0.dist-info/entry_points.txt
visual_cataloguer-0.8.0.dist-info/licenses/LICENSE
visual_cataloguer-0.8.0.dist-info/RECORD
