Metadata-Version: 2.4
Name: visual-cataloguer
Version: 0.8.0
Summary: Batch catalogue physical collections using visual dividers (QR codes) and automated image processing
License: MIT
License-File: LICENSE
Keywords: cataloguing,collection,inventory,ocr,qr-code,retro-games
Classifier: Development Status :: 3 - Alpha
Classifier: Environment :: Console
Classifier: Intended Audience :: End Users/Desktop
Classifier: Topic :: Database
Classifier: Topic :: Multimedia :: Graphics :: Capture
Requires-Python: >=3.11
Requires-Dist: anthropic>=0.75.0
Requires-Dist: click>=8.0.0
Requires-Dist: exifread>=3.0.0
Requires-Dist: numpy>=1.24.0
Requires-Dist: opencv-python>=4.8.0
Requires-Dist: pillow>=10.0.0
Requires-Dist: pytesseract>=0.3.10
Requires-Dist: rawpy>=0.18.0
Requires-Dist: rich>=13.0.0
Requires-Dist: tqdm>=4.65.0
Provides-Extra: dev
Requires-Dist: mypy>=1.13.0; extra == 'dev'
Requires-Dist: pytest-cov>=4.0.0; extra == 'dev'
Requires-Dist: pytest>=8.0.0; extra == 'dev'
Requires-Dist: ruff>=0.8.0; extra == 'dev'
Requires-Dist: types-pillow; extra == 'dev'
Provides-Extra: web
Requires-Dist: fastapi>=0.100.0; extra == 'web'
Requires-Dist: python-multipart>=0.0.6; extra == 'web'
Requires-Dist: sqlalchemy>=2.0.0; extra == 'web'
Requires-Dist: uvicorn>=0.23.0; extra == 'web'
